ImageGen/__init__.py
ImageGen/api_client.py
ImageGen/image_generation.py
tests/__init__.py
tests/test_image_generation.py
FAImageGen-1.0.0.dist-info/LICENSE
FAImageGen-1.0.0.dist-info/METADATA
FAImageGen-1.0.0.dist-info/WHEEL
FAImageGen-1.0.0.dist-info/top_level.txt
FAImageGen-1.0.0.dist-info/RECORD
