Metadata-Version: 2.1
Name: FAImageGen
Version: 1.0.0
Summary: Python SDK for ImageGen
Home-page: https://github.com/FotographerAI/ImageGen-sdk/
Author: Saliou Kane
Author-email: saliou@fotographer.ai
Classifier: Programming Language :: Python :: 3
Classifier: License :: OSI Approved :: MIT License
Classifier: Operating System :: OS Independent
Requires-Python: >=3.6
License-File: LICENSE
Requires-Dist: requests
